LICENSE
MANIFEST.in
README.md
setup.py
badgr/__init__.py
badgr/context_processors.py
badgr/settings.py
badgr/templates/badgr/photos.html
django_badgr.egg-info/PKG-INFO
django_badgr.egg-info/SOURCES.txt
django_badgr.egg-info/dependency_links.txt
django_badgr.egg-info/not-zip-safe
django_badgr.egg-info/requires.txt
django_badgr.egg-info/top_level.txt