Metadata-Version: 1.1
Name: django-badgr
Version: 1.0
Summary: A resuable Django application used to display a Flickr badge.
Home-page: https://github.com/pigmonkey/django-badgr
Author: Peter Hogg
Author-email: peter@havenaut.net
License: UNKNOWN
Platform: UNKNOWN
Classifier: Programming Language :: Python
Classifier: License :: OSI Approved :: BSD License
Classifier: Operating System :: OS Independent
Classifier: Development Status :: 5 - Production/Stable
Classifier: Framework :: Django
